pylon2mqtt/__init__.py
pylon2mqtt/cli.py
pylon2mqtt/protocol.py
pylon2mqtt/usbutils.py
pylon2mqtt-0.2.0.dist-info/METADATA
pylon2mqtt-0.2.0.dist-info/WHEEL
pylon2mqtt-0.2.0.dist-info/entry_points.txt
pylon2mqtt-0.2.0.dist-info/licenses/LICENSE.txt
pylon2mqtt-0.2.0.dist-info/RECORD
