Metadata-Version: 2.4
Name: pylon2mqtt
Version: 0.2.0
Summary: Pylon Battery statistics to MQTT exporter
Project-URL: Homepage, https://github.com/mensi/pylon2mqtt
Author-email: Manuel Stocker <mensi@mensi.ch>
License:                                  Apache License
License-File: LICENSE.txt
Requires-Python: >=3.10
Requires-Dist: click>=8.1.8
Requires-Dist: paho-mqtt>=2.1.0
Requires-Dist: pyserial>=3.5
Requires-Dist: pyudev>=0.24.3; sys_platform == 'linux'
